kutana/__init__.py
kutana/__main__.py
kutana/backend.py
kutana/backends/__init__.py
kutana/backends/debug.py
kutana/backends/telegram.py
kutana/backends/vkontakte/__init__.py
kutana/backends/vkontakte/base.py
kutana/backends/vkontakte/callback.py
kutana/backends/vkontakte/extensions.py
kutana/backends/vkontakte/longpoll.py
kutana/context.py
kutana/decorators.py
kutana/exceptions.py
kutana/handler.py
kutana/helpers.py
kutana/kutana.py
kutana/loaders.py
kutana/plugin.py
kutana/router.py
kutana/storage.py
kutana/storages/__init__.py
kutana/storages/memory.py
kutana/storages/mongodb.py
kutana/storages/sqlite.py
kutana/update.py
kutana-6.0.1.dist-info/LICENCE
kutana-6.0.1.dist-info/METADATA
kutana-6.0.1.dist-info/WHEEL
kutana-6.0.1.dist-info/entry_points.txt
kutana-6.0.1.dist-info/RECORD
