Metadata-Version: 2.1
Name: kutana
Version: 6.0.1
Summary: The library for developing systems for messengers and social networks
License: MIT
Author: Michael Kryukov
Author-email: kryukov.ms@ya.ru
Requires-Python: >=3.8,<4.0
Classifier: License :: OSI Approved :: MIT License
Classifier: Programming Language :: Python :: 3
Classifier: Programming Language :: Python :: 3.8
Classifier: Programming Language :: Python :: 3.9
Classifier: Programming Language :: Python :: 3.10
Classifier: Programming Language :: Python :: 3.11
Classifier: Programming Language :: Python :: 3.12
Requires-Dist: aiohttp (>=3.6,<4.0)
Requires-Dist: httpx (>=0.24.1,<0.25.0)
Requires-Dist: motor (>=3.3.2,<4.0.0)
Requires-Dist: pyyaml (>=6.0,<7.0)
